samp_client/__init__.py
samp_client/client.py
samp_client/constants.py
samp_client/exceptions.py
samp_client/models.py
samp_client/utils.py
samp_client-3.0.1.dist-info/LICENSE
samp_client-3.0.1.dist-info/METADATA
samp_client-3.0.1.dist-info/WHEEL
samp_client-3.0.1.dist-info/top_level.txt
samp_client-3.0.1.dist-info/RECORD
