Metadata-Version: 2.1
Name: samp-client
Version: 3.0.1
Summary: SA-MP API client for python supporting both query and RCON APIs
Home-page: https://github.com/mick88/samp-client
Author: Michal Dabski
Author-email: contact@michaldabski.com
License: MIT
Project-URL: Source, https://github.com/mick88/samp-client
Project-URL: Tracker, https://github.com/mick88/samp-client/issues
Platform: UNKNOWN
Classifier: Programming Language :: Python :: 3
Classifier: Programming Language :: Python :: 3.4
Classifier: Programming Language :: Python :: 3.5
Classifier: Programming Language :: Python :: 3.6
Classifier: Programming Language :: Python :: 3.7
Classifier: Programming Language :: Python :: 3.8
